cgelib/__init__.py
cgelib/alignment/__init__.py
cgelib/alignment/aligner.py
cgelib/alignment/read_alignment.py
cgelib/alignment/KMA/__init__.py
cgelib/alignment/KMA/alignment_files.py
cgelib/alignment/KMA/read_files.py
cgelib/alignment/blast/__init__.py
cgelib/alignment/blast/alignment_files.py
cgelib/alignment/blast/read_files.py
cgelib/applications/Blast.py
cgelib/applications/KMA.py
cgelib/applications/__init__.py
cgelib/applications/command.py
cgelib/output/__init__.py
cgelib/output/exceptions.py
cgelib/output/parserdict.py
cgelib/output/result.py
cgelib/output/valueparsers.py
cgelib/output/templates_json/beone/beone.json
cgelib/output/templates_json/beone/example.json
cgelib/output/test_data/__init__.py
cgelib/output/test_data/test_val_parse_fail.py
cgelib/sequence/Feature.py
cgelib/sequence/SeqHit.py
cgelib/sequence/__init__.py
cgelib/utils/__init__.py
cgelib/utils/file_mixin.py
cgelib/utils/format_mixin.py
cgelib/utils/loaders_mixin.py
cgelib/utils/pliers_mixin.py
cgelib/utils/savers_mixin.py
cgelib/utils/transformer_mixin.py
cgelib-0.7.5.dist-info/LICENSE.txt
cgelib-0.7.5.dist-info/METADATA
cgelib-0.7.5.dist-info/WHEEL
cgelib-0.7.5.dist-info/top_level.txt
cgelib-0.7.5.dist-info/RECORD
