Metadata-Version: 2.1
Name: cgelib
Version: 0.7.5
Summary: Description of my package
Home-page: https://bitbucket.org/genomicepidemiology/cgelib.git
Author: Center for Genomic Epidemiology
Author-email: food-cgehelp@dtu.dk
Project-URL: Bug Tracker, https://bitbucket.org/genomicepidemiology/cgelib/issues
Project-URL: CGE website, http://genomicepidemiology.org
Project-URL: CGE webtools, http://genomicepidemiology.org/services
Classifier: Programming Language :: Python :: 3
Classifier: License :: OSI Approved :: Apache Software License
Classifier: Operating System :: Unix
Classifier: Topic :: Scientific/Engineering :: Bio-Informatics
Classifier: Development Status :: 3 - Alpha
Requires-Python: >=3.6
License-File: LICENSE.txt
Requires-Dist: python-dateutil
Requires-Dist: GitPython
